flash_attn/__init__.py
flash_attn/bert_padding.py
flash_attn/layers/__init__.py
flash_attn/layers/rotary.py
flash_attn/ops/__init__.py
flash_attn/ops/triton/__init__.py
flash_attn/ops/triton/rotary.py
flash_attn_triton/__init__.py
flash_attn_triton/flash_attn_interface.py
flash_attn_triton/triton_kernel/__init__.py
flash_attn_triton/triton_kernel/attention_kernel.py
flash_attn_triton/triton_kernel/flash_attn_dao.py
flash_attn_triton-0.1.1.dist-info/licenses/LICENSE
flash_attn_triton-0.1.1.dist-info/METADATA
flash_attn_triton-0.1.1.dist-info/WHEEL
flash_attn_triton-0.1.1.dist-info/top_level.txt
flash_attn_triton-0.1.1.dist-info/RECORD
