Metadata-Version: 2.4
Name: flash-attn-triton
Version: 0.1.1
Summary: Triton-based backend for Flash Attention 2
Home-page: https://github.com/rationalism/flash-attn-triton
Author: Alyssa Vance
Author-email: alyssamvance@gmail.com
Project-URL: Bug Tracker, https://github.com/rationalism/flash-attn-triton/issues
Classifier: Programming Language :: Python :: 3
Classifier: License :: OSI Approved :: BSD License
Classifier: Operating System :: OS Independent
Requires-Python: >=3.8
License-File: LICENSE
Requires-Dist: einops
Requires-Dist: torch>=2.6.0
Requires-Dist: triton>=3.2.0
Requires-Dist: packaging
Requires-Dist: pytest
Dynamic: author
Dynamic: author-email
Dynamic: classifier
Dynamic: description
Dynamic: description-content-type
Dynamic: home-page
Dynamic: license-file
Dynamic: project-url
Dynamic: requires-dist
Dynamic: requires-python
Dynamic: summary
